bashpy/_init_.py
bashpy/main.py
bashpy_SaracenRhue-0.0.1.dist-info/LICENSE
bashpy_SaracenRhue-0.0.1.dist-info/METADATA
bashpy_SaracenRhue-0.0.1.dist-info/WHEEL
bashpy_SaracenRhue-0.0.1.dist-info/top_level.txt
bashpy_SaracenRhue-0.0.1.dist-info/RECORD
