Metadata-Version: 2.1
Name: bashpy-SaracenRhue
Version: 0.0.1
Summary: Run bash commands using python functions
Author-email: SaracenRhue <author@example.com>
Project-URL: Homepage, https://github.com/saracenrhue/bashpy
Project-URL: Bug Tracker, https://github.com/saracenrhue/bashpy/issues
Classifier: Programming Language :: Python :: 3
Classifier: License :: OSI Approved :: MIT License
Classifier: Operating System :: OS Independent
Requires-Python: >=3.9
License-File: LICENSE
